pynumstim/__init__.py
pynumstim/_data_sets.py
pynumstim/_mplist.py
pynumstim/_number.py
pynumstim/_problem.py
pynumstim/eprime.py
pynumstim/image.py
pynumstim/datasets/Ahren_Jackson_79.toml
pynumstim/datasets/Lindemann_Tira_10.toml
pynumstim-0.2.10.dist-info/LICENSE
pynumstim-0.2.10.dist-info/WHEEL
pynumstim-0.2.10.dist-info/METADATA
pynumstim-0.2.10.dist-info/RECORD
