Metadata-Version: 2.1
Name: pynumstim
Version: 0.2.10
Summary: Python library to create symbolic number and arithmetic stimuli for psychological experiments
Keywords: experiment control,open science,experimental psychology
Author-email: Oliver Lindemann <lindemann@essb.eur.nl>
Requires-Python: >=3.10
Classifier: License :: OSI Approved :: MIT License
Classifier: Programming Language :: Python :: 3
Classifier: Operating System :: OS Independent
Requires-Dist: pandas>=2.1
Requires-Dist: toml>=0.10.2
Requires-Dist: sympy>=1.12
Project-URL: Documentation, https://github.com/lindemann09/PyNumStim
Project-URL: Source, https://github.com/lindemann09/PyNumStim
